picoquake/__init__.py
picoquake/__main__.py
picoquake/analisys.py
picoquake/cli.py
picoquake/configuration.py
picoquake/data.py
picoquake/exceptions.py
picoquake/interface.py
picoquake/plot.py
picoquake/utils.py
picoquake/msg/__init__.py
picoquake/msg/messages_pb2.py
picoquake/msg/nanopb_pb2.py
picoquake-1.2.0.dist-info/METADATA
picoquake-1.2.0.dist-info/WHEEL
picoquake-1.2.0.dist-info/entry_points.txt
picoquake-1.2.0.dist-info/licenses/LICENSE.txt
picoquake-1.2.0.dist-info/RECORD
