Metadata-Version: 2.4
Name: picoquake
Version: 1.2.0
Summary: PicoQuake USB vibration sensor library.
Project-URL: Repository, https://github.com/PLab-SI/PicoQuake
Project-URL: Documentation, https://plab-si.github.io/PicoQuake/
Author-email: Nejc Planinsek <nejc@plab.si>
License-File: LICENSE.txt
Keywords: IMU,accelerometer,data acquisition,gyroscope,picoquake,vibration
Classifier: Development Status :: 4 - Beta
Classifier: Intended Audience :: Science/Research
Classifier: License :: OSI Approved :: GNU General Public License v3 (GPLv3)
Classifier: Operating System :: OS Independent
Classifier: Programming Language :: Python :: 3
Classifier: Topic :: Software Development :: Libraries
Classifier: Topic :: Software Development :: Libraries :: Python Modules
Requires-Python: >=3.9
Requires-Dist: cobs~=1.2
Requires-Dist: protobuf~=6.31
Requires-Dist: pyserial~=3.5
Requires-Dist: tomli~=1.1; python_version < '3.11'
Provides-Extra: plot
Requires-Dist: matplotlib~=3.9; extra == 'plot'
Requires-Dist: numpy~=2.0; extra == 'plot'
Requires-Dist: scipy~=1.13; extra == 'plot'
Provides-Extra: test
Requires-Dist: matplotlib~=3.9; extra == 'test'
Requires-Dist: numpy~=2.0; extra == 'test'
Requires-Dist: pytest~=8.4; extra == 'test'
Requires-Dist: scipy~=1.13; extra == 'test'
